runorm/__init__.py
runorm/number_to_word.py
runorm/rule_normalizer.py
runorm/runorm.py
runorm-1.1.dist-info/LICENSE
runorm-1.1.dist-info/WHEEL
runorm-1.1.dist-info/METADATA
runorm-1.1.dist-info/RECORD
