Metadata-Version: 2.1
Name: runorm
Version: 1.1
Summary: Russian text normalizer
Author-email: Denis Petrov <arduino4b@gmail.com>
Classifier: License :: OSI Approved :: Apache Software License
Requires-Dist: transformers
Requires-Dist: razdel
Requires-Dist: torch
Requires-Dist: sentencepiece
Project-URL: Home, https://github.com/Den4ikAI/runorm
